{
    "title": "Document Control Best Practices for Construction Projects",
    "slug": "document-control-best-practices",
    "date": "2023-01-11",
    "image": "https://images.unsplash.com/photo-1454165804606-c3d57bc86b40?w=800&h=600&fit=crop",
    "categories": [
        "Document Control"
    ],
    "tags": [
        "document",
        "control",
        "management",
        "construction"
    ],
    "excerpt": "Discover essential document control best practices for construction projects. Learn about version control, document distribution, tracking systems, and maintaining accurate project documentation.",
    "content": "<div style=\"text-align: left; direction: ltr; max-width: 100%;\"><h2>Document Control Best Practices</h2>\n<p>Effective document control is fundamental to construction project success. Proper document management ensures all stakeholders work from current, accurate information, reducing errors, delays, and disputes. Implementing best practices in document control creates a foundation for efficient project communication and execution.</p>\n\n<p>The importance of document control increases exponentially with project complexity. Large projects generate thousands of documents including drawings, specifications, submittals, RFIs, change orders, and correspondence. Without systematic control, documents become outdated, versions get confused, and teams work from incorrect information—leading to costly mistakes and delays.</p>\n\n<h3>Version Control Systems</h3>\n<p>Maintaining accurate version control prevents costly errors:</p>\n<ul>\n<li><strong>Naming Conventions:</strong> Establish clear, consistent file naming standards</li>\n<li><strong>Revision Tracking:</strong> Track all document revisions and changes</li>\n<li><strong>Master Document Registers:</strong> Maintain centralized logs of all documents</li>\n<li><strong>Obsolete Document Management:</strong> Archive old versions while maintaining access</li>\n<li><strong>Change Notification:</strong> Notify stakeholders of document updates</li>\n</ul>\n\n<h3>Document Distribution Procedures</h3>\n<p>Systematic distribution ensures proper access:</p>\n<ul>\n<li><strong>Distribution Matrices:</strong> Define who receives which documents</li>\n<li><strong>Transmittal Management:</strong> Track all document distributions formally</li>\n<li><strong>Access Control:</strong> Restrict access to sensitive or confidential documents</li>\n<li><strong>Delivery Confirmation:</strong> Verify receipt of transmitted documents</li>\n<li><strong>Electronic Distribution:</strong> Use secure electronic distribution systems</li>\n</ul>\n\n<h3>Document Organization and Storage</h3>\n<p>Well-organized systems improve efficiency:</p>\n<ul>\n<li><strong>Folder Structure:</strong> Create logical, consistent folder hierarchies</li>\n<li><strong>Categorization:</strong> Organize documents by type, discipline, and phase</li>\n<li><strong>Metadata Management:</strong> Tag documents with searchable metadata</li>\n<li><strong>Cloud Storage:</strong> Use cloud-based storage for accessibility</li>\n<li><strong>Backup Systems:</strong> Implement regular backup and disaster recovery</li>\n</ul>\n\n<h3>Drawing Management</h3>\n<p>Construction drawings require special attention:</p>\n<ul>\n<li><strong>Drawing Logs:</strong> Maintain comprehensive drawing registers</li>\n<li><strong>Approval Workflows:</strong> Track drawing approval status</li>\n<li><strong>Issue Management:</strong> Control official issue dates and versions</li>\n<li><strong>As-Built Tracking:</strong> Document as-built conditions and changes</li>\n<li><strong>Drawing Comparison:</strong> Use tools to compare drawing versions</li>\n</ul>\n\n<h3>Specification Management</h3>\n<p>Specifications must stay current and accessible:</p>\n<ul>\n<li><strong>Specification Registers:</strong> Track all project specifications</li>\n<li><strong>Amendment Management:</strong> Manage specification addenda and changes</li>\n<li><strong>Cross-Reference:</strong> Link specifications to drawings and submittals</li>\n<li><strong>Standard Libraries:</strong> Maintain standard specification libraries</li>\n</ul>\n\n<h3>Document Control Software</h3>\n<p>Modern tools streamline document management:</p>\n<ul>\n<li><strong>Bluebeam Revu:</strong> PDF markup and collaboration tools</li>\n<li><strong>Procore:</strong> Comprehensive construction management platform</li>\n<li><strong>Autodesk Construction Cloud:</strong> BIM 360 document management</li>\n<li><strong>Document Management Systems:</strong> Enterprise document control platforms</li>\n<li><strong>Custom Solutions:</strong> Tailored systems for specific project needs</li>\n</ul>\n\n<h3>Quality Assurance in Document Control</h3>\n<p>Quality procedures ensure accuracy:</p>\n<ul>\n<li><strong>Review Procedures:</strong> Establish review and approval workflows</li>\n<li><strong>Error Checking:</strong> Implement quality checks before distribution</li>\n<li><strong>Standard Compliance:</strong> Ensure documents meet project standards</li>\n<li><strong>Audit Trails:</strong> Maintain records of all document activities</li>\n</ul>\n\n<h3>Communication and Training</h3>\n<p>Effective document control requires team alignment:</p>\n<ul>\n<li><strong>Procedure Documentation:</strong> Document all document control procedures</li>\n<li><strong>Team Training:</strong> Train all team members on procedures</li>\n<li><strong>Regular Updates:</strong> Communicate changes to procedures</li>\n<li><strong>Access Support:</strong> Provide support for document access and use</li>\n</ul>\n\n<h3>Why Choose Professional Document Control Services?</h3>\n<p>Professional document control requires specialized expertise in construction workflows and document management systems. ASISA's document control team understands construction processes and can implement efficient document management procedures. We help establish systems, train teams, and provide ongoing support.</p>\n\n<h3>ASISA's Document Control Services</h3>\n<p>ASISA provides comprehensive document control services including document management system setup, version control implementation, distribution management, and training. Our offshore support offers cost-effective access to skilled professionals who understand construction document control best practices.</p>\n\n<p>Contact ASISA to learn how our document control services can improve organization and efficiency in your construction projects. We help establish robust document management systems that reduce errors and improve project communication.</p></div>"
}